azure/mgmt/weightsandbiases/__init__.py
azure/mgmt/weightsandbiases/_client.py
azure/mgmt/weightsandbiases/_configuration.py
azure/mgmt/weightsandbiases/_model_base.py
azure/mgmt/weightsandbiases/_patch.py
azure/mgmt/weightsandbiases/_serialization.py
azure/mgmt/weightsandbiases/_version.py
azure/mgmt/weightsandbiases/py.typed
azure/mgmt/weightsandbiases/aio/__init__.py
azure/mgmt/weightsandbiases/aio/_client.py
azure/mgmt/weightsandbiases/aio/_configuration.py
azure/mgmt/weightsandbiases/aio/_patch.py
azure/mgmt/weightsandbiases/aio/operations/__init__.py
azure/mgmt/weightsandbiases/aio/operations/_operations.py
azure/mgmt/weightsandbiases/aio/operations/_patch.py
azure/mgmt/weightsandbiases/models/__init__.py
azure/mgmt/weightsandbiases/models/_enums.py
azure/mgmt/weightsandbiases/models/_models.py
azure/mgmt/weightsandbiases/models/_patch.py
azure/mgmt/weightsandbiases/operations/__init__.py
azure/mgmt/weightsandbiases/operations/_operations.py
azure/mgmt/weightsandbiases/operations/_patch.py
azure_mgmt_weightsandbiases-1.0.0b1.dist-info/LICENSE
azure_mgmt_weightsandbiases-1.0.0b1.dist-info/METADATA
azure_mgmt_weightsandbiases-1.0.0b1.dist-info/WHEEL
azure_mgmt_weightsandbiases-1.0.0b1.dist-info/top_level.txt
azure_mgmt_weightsandbiases-1.0.0b1.dist-info/RECORD
